w4benchmark/Decorators.py
w4benchmark/Molecule.py
w4benchmark/Params.py
w4benchmark/W4Map.py
w4benchmark/__init__.py
w4benchmark-1.0.0.dist-info/licenses/LICENSE
w4benchmark-1.0.0.dist-info/METADATA
w4benchmark-1.0.0.dist-info/WHEEL
w4benchmark-1.0.0.dist-info/top_level.txt
w4benchmark-1.0.0.dist-info/RECORD
