Metadata-Version: 2.4
Name: w4benchmark
Version: 1.0.0
Home-page: https://github.com/Lukas-Petervary/w4benchmark/
Author: Lukas Petervary
License: CC BY-NC 4.0
Classifier: Development Status :: 1 - Planning
Classifier: Intended Audience :: Science/Research
Classifier: License :: Other/Proprietary License
Classifier: Programming Language :: Python :: 3
License-File: LICENSE
Requires-Dist: numpy>=2.2.4
Dynamic: author
Dynamic: classifier
Dynamic: description
Dynamic: description-content-type
Dynamic: home-page
Dynamic: license
Dynamic: license-file
Dynamic: requires-dist
